Workbook

Sheet Start Here
A1: INVESTMENT PROJECT
A3: What are we trying to answer?
A4: Is the company growing, what might it be worth, and what could a PE investor earn in a simple example?
A6: Use these tabs in order:
A7: 1. Company Data | B7: Five years of company financials. These are the starting facts.
A8: 2. Simple Analysis | B8: See revenue growth and EBITDA margin. The formulas do the maths.
A9: 3. Forecast | B9: Make a simple estimate for the next three years.
A10: 4. Simple Valuation | B10: Estimate company value using EBITDA × an assumed multiple.
A11: 5. PE Example | B11: Pretend a PE fund buys and sells the company; calculate MOIC.
A12: 6. Dashboard Data | B12: Clean table to import into Power BI.
A15: Important:
A16: This is a learning case, not investment advice and not a claim that Tata Consumer is for sale.
A17: Historical figures are from the previous project dataset based on company annual reports; check the annual reports before using externally.
A18: Forecast growth, valuation multiple, debt and exit assumptions are made up for practice and are clearly labeled.

Sheet Company Data
A1: COMPANY DATA — HISTORICAL FIGURES (₹ CRORE)
A3: Financial year | B3: Revenue | C3: EBITDA | D3: PAT | E3: Source type | F3: Notes
A4: FY22 | B4: 12425 | C4: 1749 | D4: 1076 | E4: Company reported | F4: Historical
A5: FY23 | B5: 13783 | C5: 1874 | D5: 1347 | E5: Company reported | F5: Historical
A6: FY24 | B6: 15206 | C6: 2323 | D6: 1215 | E6: Company reported | F6: Historical
A7: FY25 | B7: 17618 | C7: 2502 | D7: 1287 | E7: Company reported | F7: Historical
A8: FY26 | B8: 20290 | C8: 2815 | D8: 1547 | E8: Company reported | F8: Historical

Sheet Simple Analysis
A1: SIMPLE ANALYSIS — LET THE FORMULAS DO THE MATH
A3: Year | B3: Revenue | C3: Revenue growth | D3: EBITDA | E3: EBITDA margin
A4: ='Company Data'!A4 -> FY22 | B4: ='Company Data'!B4 -> 12425 | C4: — | D4: ='Company Data'!C4 -> 1749 | E4: =D4/B4 -> 0.14076459
A5: ='Company Data'!A5 -> FY23 | B5: ='Company Data'!B5 -> 13783 | C5: =B5/B4-1 -> 0.10929577 | D5: ='Company Data'!C5 -> 1874 | E5: =D5/B5 -> 0.13596459
A6: ='Company Data'!A6 -> FY24 | B6: ='Company Data'!B6 -> 15206 | C6: =B6/B5-1 -> 0.10324313 | D6: ='Company Data'!C6 -> 2323 | E6: =D6/B6 -> 0.15276864
A7: ='Company Data'!A7 -> FY25 | B7: ='Company Data'!B7 -> 17618 | C7: =B7/B6-1 -> 0.1586216 | D7: ='Company Data'!C7 -> 2502 | E7: =D7/B7 -> 0.14201385
A8: ='Company Data'!A8 -> FY26 | B8: ='Company Data'!B8 -> 20290 | C8: =B8/B7-1 -> 0.15166307 | D8: ='Company Data'!C8 -> 2815 | E8: =D8/B8 -> 0.13873829
A11: What does this tell us?
A12: Revenue growth = how quickly sales are increasing. EBITDA margin = how much EBITDA the company makes from every ₹100 of revenue.

Sheet Forecast
A1: SIMPLE 3-YEAR FORECAST — PRACTICE, NOT A PROMISE
A3: Revenue growth assumption | B3: 0.08 | C3: Yellow cells are assumptions you can change.
A4: EBITDA margin assumption | B4: 0.145
A6: Year | B6: Revenue | C6: EBITDA margin | D6: EBITDA | E6: What it means
A7: FY27 | B7: ='Company Data'!B8*(1+$B$3) -> 21913.2 | C7: =$B$4 -> 0.145 | D7: =B7*C7 -> 3177.414 | E7: Estimated, not actual
A8: FY28 | B8: =B7*(1+$B$3) -> 23666.256 | C8: =$B$4 -> 0.145 | D8: =B8*C8 -> 3431.6071 | E8: Estimated, not actual
A9: FY29 | B9: =B8*(1+$B$3) -> 25559.556 | C9: =$B$4 -> 0.145 | D9: =B9*C9 -> 3706.1357 | E9: Estimated, not actual
A12: Simple explanation:
A13: We assume sales grow by 8% each year and EBITDA stays at 14.5% of sales. These are practice assumptions, not management guidance.

Sheet Simple Valuation
A1: COMPANY VALUE — ONE MULTIPLE ONLY
A3: FY26 EBITDA (₹ Cr) | B3: ='Company Data'!C8 -> 2815
A4: Assumed EV / EBITDA multiple | B4: 20
A5: Estimated Enterprise Value (₹ Cr) | B5: =B3*B4 -> 56300
A7: How to understand it:
A8: If a business makes ₹100 EBITDA and we use 20×, its estimated enterprise value is ₹2,000.
A10: The 20× multiple is a simple learning assumption, not a live market quote or a formal valuation.

Sheet PE Example
A1: A VERY SIMPLE PE BUY-AND-SELL EXAMPLE
A2: Item | B2: Value
A3: Purchase enterprise value | B3: ='Simple Valuation'!B5 -> 56300
A4: Debt used to buy (30%) | B4: =B3*30% -> 16890
A5: PE investor's own money | B5: =B3-B4 -> 39410
A6: FY29 forecast EBITDA | B6: =Forecast!D9 -> 3706.1357
A7: Exit EV / EBITDA multiple | B7: 20
A8: Estimated selling value | B8: =B6*B7 -> 74122.714
A9: Debt remaining at sale | B9: =B4*70% -> 11823
A10: Money received by PE fund | B10: =B8-B9 -> 62299.714
A11: MOIC | B11: =B10/B5 -> 1.5808098
A14: Remember:
A15: This is a simplified illustration. We are not modeling interest, fees, taxes or a full debt repayment schedule.
